{"table":[{"team1":"Sharks","score1":"2","team2":"Stars","score2":"2","progress":"ongoing","time":"6:38 - 3rd","network":"NHLPP|ESPN+","link":"https://www.espn.com/watch/"},{"team1":"Penguins","score1":"0","team2":"Flames","score2":"0","progress":"ongoing","time":"7:22 - 1st","network":"NHLPP|ESPN+","link":"https://www.espn.com/watch/"},{"team1":"Blue Jackets","score1":"5","team2":"Blackhawks","score2":"2","progress":"ongoing","time":"0:27 - 3rd","network":"NHLPP|ESPN+","link":"https://www.espn.com/watch/"},{"team1":"Rangers","score1":"3","team2":"Maple Leafs","score2":"4","progress":"ended","time":"Final/SO"},{"team1":"Oilers","score1":"2","team2":"Kraken","score2":"1","progress":"ended","time":"Final"},{"team1":"Canadiens","score1":"3","team2":"Lightning","score2":"4","progress":"ended","time":"Final/SO"},{"team1":"Jets","score1":"5","team2":"Hurricanes","score2":"3","progress":"ended","time":"Final"},{"team1":"Wild","score1":"1","team2":"Blues","score2":"3","progress":"ended","time":"Final"},{"team1":"Senators","score1":"2","team2":"Flyers","score2":"4","progress":"ended","time":"Final"},{"team1":"Panthers","score1":"4","team2":"Red Wings","score2":"0","progress":"ended","time":"Final"},{"team1":"Avalanche","score1":"1","team2":"Predators","score2":"5","progress":"ended","time":"Final"},{"team1":"Bruins","score1":"1","team2":"Islanders","score2":"5","progress":"ended","time":"Final"},{"team1":"Golden Knights","score1":"2","team2":"Sabres","score2":"7","progress":"ended","time":"Final"},{"date":"March 2, 2024"}]}